chencode/__init__.py
chencode/__main__.py
chencode/frame.py
chencode/lts.py
chencode/main.py
chencode-0.0.1.dist-info/METADATA
chencode-0.0.1.dist-info/WHEEL
chencode-0.0.1.dist-info/top_level.txt
chencode-0.0.1.dist-info/RECORD
