Metadata-Version: 2.1
Name: chencode
Version: 0.0.1
Summary: A easy method to encrypt/decrypt chinese letters based on thier PinYin
Home-page: https://github.com/jeefies/chencode
Author: Jeefy
Author-email: Jeefy <jeefy163@163.com>
Project-URL: Homepage, https://github.com/jeefies/chencode
Project-URL: Bug Tracker, https://github.com/jeefies/chencode/issues
Classifier: Programming Language :: Python :: 3
Requires-Python: >3.4
Requires-Dist: pypinyin
